extopy/__init__.py
extopy/py.typed
extopy/com/extopy/models/application/Client.py
extopy/com/extopy/models/application/CodeInEmail.py
extopy/com/extopy/models/application/Email.py
extopy/com/extopy/models/application/ExtopyEnvironment.py
extopy/com/extopy/models/application/SearchOptions.py
extopy/com/extopy/models/auth/AuthRequest.py
extopy/com/extopy/models/auth/AuthToken.py
extopy/com/extopy/models/auth/ClientForUser.py
extopy/com/extopy/models/auth/LoginPayload.py
extopy/com/extopy/models/auth/RefreshTokenPayload.py
extopy/com/extopy/models/auth/RegisterCodePayload.py
extopy/com/extopy/models/auth/RegisterPayload.py
extopy/com/extopy/models/auth/SessionPayload.py
extopy/com/extopy/models/notifications/Notification.py
extopy/com/extopy/models/notifications/TokenInNotification.py
extopy/com/extopy/models/posts/LikeInPost.py
extopy/com/extopy/models/posts/Post.py
extopy/com/extopy/models/posts/PostPayload.py
extopy/com/extopy/models/timelines/Timeline.py
extopy/com/extopy/models/users/ClientInUser.py
extopy/com/extopy/models/users/CreateUserPayload.py
extopy/com/extopy/models/users/FollowerInUser.py
extopy/com/extopy/models/users/FollowerInUserContext.py
extopy/com/extopy/models/users/UpdateUserPayload.py
extopy/com/extopy/models/users/User.py
extopy/com/extopy/models/users/UserContext.py
extopy-0.1.5.dist-info/METADATA
extopy-0.1.5.dist-info/WHEEL
extopy-0.1.5.dist-info/top_level.txt
extopy-0.1.5.dist-info/RECORD
