Metadata-Version: 2.4
Name: extopy
Version: 0.1.5
Summary: Auto-generated Pydantic project from Kotlin using guimauvedigital/zodable
Requires-Python: >=3.9
Requires-Dist: pydantic
Requires-Dist: uuid
Requires-Dist: typing
Requires-Dist: datetime
